{
  "address": "2mbuH8RZ99bkBZozkvj5AzadS6jsC1BS13m3NjSnqY9r",
  "metadata": {
    "name": "safetrade_capstone",
    "version": "0.1.0",
    "spec": "0.1.0",
    "description": "Created with Anchor"
  },
  "instructions": [
    {
      "name": "cancel_escrow",
      "discriminator": [
        156,
        203,
        54,
        179,
        38,
        72,
        33,
        21
      ],
      "accounts": [
        {
          "name": "seller",
          "writable": true,
          "signer": true
        },
        {
          "name": "escrow",
          "writable": true,
          "pda": {
            "seeds": [
              {
                "kind": "const",
                "value": [
                  101,
                  115,
                  99,
                  114,
                  111,
                  119
                ]
              },
              {
                "kind": "account",
                "path": "seller"
              },
              {
                "kind": "arg",
                "path": "listing_id"
              }
            ]
          }
        }
      ],
      "args": [
        {
          "name": "_listing_id",
          "type": "u64"
        }
      ]
    },
    {
      "name": "claim_after_expire",
      "discriminator": [
        214,
        112,
        155,
        158,
        1,
        232,
        9,
        0
      ],
      "accounts": [
        {
          "name": "claimer",
          "writable": true,
          "signer": true
        },
        {
          "name": "seller",
          "writable": true
        },
        {
          "name": "escrow",
          "writable": true,
          "pda": {
            "seeds": [
              {
                "kind": "const",
                "value": [
                  101,
                  115,
                  99,
                  114,
                  111,
                  119
                ]
              },
              {
                "kind": "account",
                "path": "seller"
              },
              {
                "kind": "arg",
                "path": "listing_id"
              }
            ]
          }
        },
        {
          "name": "vault",
          "writable": true,
          "pda": {
            "seeds": [
              {
                "kind": "const",
                "value": [
                  118,
                  97,
                  117,
                  108,
                  116
                ]
              },
              {
                "kind": "account",
                "path": "escrow"
              }
            ]
          }
        },
        {
          "name": "system_program",
          "address": "11111111111111111111111111111111"
        }
      ],
      "args": [
        {
          "name": "_listing_id",
          "type": "u64"
        },
        {
          "name": "vault_bump",
          "type": "u8"
        }
      ]
    },
    {
      "name": "complete_escrow",
      "discriminator": [
        158,
        211,
        102,
        36,
        244,
        24,
        103,
        163
      ],
      "accounts": [
        {
          "name": "buyer",
          "writable": true,
          "signer": true
        },
        {
          "name": "seller",
          "writable": true
        },
        {
          "name": "escrow",
          "writable": true,
          "pda": {
            "seeds": [
              {
                "kind": "const",
                "value": [
                  101,
                  115,
                  99,
                  114,
                  111,
                  119
                ]
              },
              {
                "kind": "account",
                "path": "seller"
              },
              {
                "kind": "arg",
                "path": "listing_id"
              }
            ]
          }
        },
        {
          "name": "vault",
          "writable": true,
          "pda": {
            "seeds": [
              {
                "kind": "const",
                "value": [
                  118,
                  97,
                  117,
                  108,
                  116
                ]
              },
              {
                "kind": "account",
                "path": "escrow"
              }
            ]
          }
        },
        {
          "name": "system_program",
          "address": "11111111111111111111111111111111"
        }
      ],
      "args": [
        {
          "name": "_listing_id",
          "type": "u64"
        },
        {
          "name": "vault_bump",
          "type": "u8"
        }
      ]
    },
    {
      "name": "create_escrow",
      "discriminator": [
        253,
        215,
        165,
        116,
        36,
        108,
        68,
        80
      ],
      "accounts": [
        {
          "name": "seller",
          "writable": true,
          "signer": true
        },
        {
          "name": "escrow",
          "writable": true,
          "pda": {
            "seeds": [
              {
                "kind": "const",
                "value": [
                  101,
                  115,
                  99,
                  114,
                  111,
                  119
                ]
              },
              {
                "kind": "account",
                "path": "seller"
              },
              {
                "kind": "arg",
                "path": "listing_id"
              }
            ]
          }
        },
        {
          "name": "vault",
          "writable": true,
          "pda": {
            "seeds": [
              {
                "kind": "const",
                "value": [
                  118,
                  97,
                  117,
                  108,
                  116
                ]
              },
              {
                "kind": "account",
                "path": "escrow"
              }
            ]
          }
        },
        {
          "name": "system_program",
          "address": "11111111111111111111111111111111"
        }
      ],
      "args": [
        {
          "name": "listing_id",
          "type": "u64"
        },
        {
          "name": "amount",
          "type": "u64"
        },
        {
          "name": "confirm_duration",
          "type": "i64"
        },
        {
          "name": "dispute_duration",
          "type": "i64"
        },
        {
          "name": "bump",
          "type": "u8"
        }
      ]
    },
    {
      "name": "fund_escrow",
      "discriminator": [
        155,
        18,
        218,
        141,
        182,
        213,
        69,
        201
      ],
      "accounts": [
        {
          "name": "buyer",
          "writable": true,
          "signer": true
        },
        {
          "name": "seller"
        },
        {
          "name": "escrow",
          "writable": true,
          "pda": {
            "seeds": [
              {
                "kind": "const",
                "value": [
                  101,
                  115,
                  99,
                  114,
                  111,
                  119
                ]
              },
              {
                "kind": "account",
                "path": "seller"
              },
              {
                "kind": "arg",
                "path": "listing_id"
              }
            ]
          }
        },
        {
          "name": "vault",
          "writable": true,
          "pda": {
            "seeds": [
              {
                "kind": "const",
                "value": [
                  118,
                  97,
                  117,
                  108,
                  116
                ]
              },
              {
                "kind": "account",
                "path": "escrow"
              }
            ]
          }
        },
        {
          "name": "system_program",
          "address": "11111111111111111111111111111111"
        }
      ],
      "args": [
        {
          "name": "_listing_id",
          "type": "u64"
        }
      ]
    },
    {
      "name": "raise_dispute",
      "discriminator": [
        41,
        243,
        1,
        51,
        150,
        95,
        246,
        73
      ],
      "accounts": [
        {
          "name": "initiator",
          "writable": true,
          "signer": true
        },
        {
          "name": "seller"
        },
        {
          "name": "escrow",
          "writable": true,
          "pda": {
            "seeds": [
              {
                "kind": "const",
                "value": [
                  101,
                  115,
                  99,
                  114,
                  111,
                  119
                ]
              },
              {
                "kind": "account",
                "path": "seller"
              },
              {
                "kind": "arg",
                "path": "listing_id"
              }
            ]
          }
        }
      ],
      "args": [
        {
          "name": "_listing_id",
          "type": "u64"
        }
      ]
    },
    {
      "name": "resolve_dispute",
      "discriminator": [
        231,
        6,
        202,
        6,
        96,
        103,
        12,
        230
      ],
      "accounts": [
        {
          "name": "resolver",
          "writable": true,
          "signer": true
        },
        {
          "name": "seller",
          "writable": true
        },
        {
          "name": "buyer",
          "writable": true
        },
        {
          "name": "escrow",
          "writable": true,
          "pda": {
            "seeds": [
              {
                "kind": "const",
                "value": [
                  101,
                  115,
                  99,
                  114,
                  111,
                  119
                ]
              },
              {
                "kind": "account",
                "path": "seller"
              },
              {
                "kind": "arg",
                "path": "listing_id"
              }
            ]
          }
        },
        {
          "name": "vault",
          "writable": true,
          "pda": {
            "seeds": [
              {
                "kind": "const",
                "value": [
                  118,
                  97,
                  117,
                  108,
                  116
                ]
              },
              {
                "kind": "account",
                "path": "escrow"
              }
            ]
          }
        },
        {
          "name": "system_program",
          "address": "11111111111111111111111111111111"
        }
      ],
      "args": [
        {
          "name": "_listing_id",
          "type": "u64"
        },
        {
          "name": "vault_bump",
          "type": "u8"
        }
      ]
    },
    {
      "name": "vote_on_dispute",
      "discriminator": [
        7,
        213,
        96,
        171,
        252,
        59,
        55,
        23
      ],
      "accounts": [
        {
          "name": "arbitrator",
          "writable": true,
          "signer": true
        },
        {
          "name": "seller"
        },
        {
          "name": "escrow",
          "writable": true,
          "pda": {
            "seeds": [
              {
                "kind": "const",
                "value": [
                  101,
                  115,
                  99,
                  114,
                  111,
                  119
                ]
              },
              {
                "kind": "account",
                "path": "seller"
              },
              {
                "kind": "arg",
                "path": "listing_id"
              }
            ]
          }
        },
        {
          "name": "vote_receipt",
          "writable": true,
          "pda": {
            "seeds": [
              {
                "kind": "const",
                "value": [
                  118,
                  111,
                  116,
                  101,
                  95,
                  114,
                  101,
                  99,
                  101,
                  105,
                  112,
                  116
                ]
              },
              {
                "kind": "account",
                "path": "escrow"
              },
              {
                "kind": "account",
                "path": "arbitrator"
              }
            ]
          }
        },
        {
          "name": "system_program",
          "address": "11111111111111111111111111111111"
        }
      ],
      "args": [
        {
          "name": "_listing_id",
          "type": "u64"
        },
        {
          "name": "support_seller",
          "type": "bool"
        },
        {
          "name": "bump",
          "type": "u8"
        }
      ]
    }
  ],
  "accounts": [
    {
      "name": "EscrowAccount",
      "discriminator": [
        36,
        69,
        48,
        18,
        128,
        225,
        125,
        135
      ]
    },
    {
      "name": "VoteReceipt",
      "discriminator": [
        104,
        20,
        204,
        252,
        45,
        84,
        37,
        195
      ]
    }
  ],
  "errors": [
    {
      "code": 6000,
      "name": "WrongBuyer",
      "msg": "The buyer provided does not match the escrow's buyer."
    },
    {
      "code": 6001,
      "name": "WrongSeller",
      "msg": "The seller provided does not match the escrow's seller."
    },
    {
      "code": 6002,
      "name": "InvalidStatus",
      "msg": "The escrow is not in a valid state for this action."
    },
    {
      "code": 6003,
      "name": "AlreadyHasBuyer",
      "msg": "The escrow already has a buyer assigned."
    },
    {
      "code": 6004,
      "name": "InvalidExpireAt",
      "msg": "The expiration timestamp must be in the future."
    },
    {
      "code": 6005,
      "name": "EscrowExpired",
      "msg": "The escrow has expired and can no longer be completed."
    }
  ],
  "types": [
    {
      "name": "EscrowAccount",
      "type": {
        "kind": "struct",
        "fields": [
          {
            "name": "seller",
            "type": "pubkey"
          },
          {
            "name": "buyer",
            "type": "pubkey"
          },
          {
            "name": "amount",
            "type": "u64"
          },
          {
            "name": "status",
            "type": {
              "defined": {
                "name": "TradeStatus"
              }
            }
          },
          {
            "name": "created_at",
            "type": "i64"
          },
          {
            "name": "expire_at",
            "type": "i64"
          },
          {
            "name": "confirm_duration",
            "type": "i64"
          },
          {
            "name": "dispute_duration",
            "type": "i64"
          },
          {
            "name": "dispute_initiator",
            "type": "pubkey"
          },
          {
            "name": "dispute_end_time",
            "type": "i64"
          },
          {
            "name": "votes_for_buyer",
            "type": "u64"
          },
          {
            "name": "votes_for_seller",
            "type": "u64"
          },
          {
            "name": "bump",
            "type": "u8"
          },
          {
            "name": "listing_id",
            "type": "u64"
          }
        ]
      }
    },
    {
      "name": "TradeStatus",
      "type": {
        "kind": "enum",
        "variants": [
          {
            "name": "Created"
          },
          {
            "name": "Funded"
          },
          {
            "name": "InDispute"
          },
          {
            "name": "Completed"
          },
          {
            "name": "Cancelled"
          },
          {
            "name": "Refunded"
          }
        ]
      }
    },
    {
      "name": "VoteReceipt",
      "type": {
        "kind": "struct",
        "fields": [
          {
            "name": "escrow",
            "type": "pubkey"
          },
          {
            "name": "arbitrator",
            "type": "pubkey"
          },
          {
            "name": "support_seller",
            "type": "bool"
          },
          {
            "name": "bump",
            "type": "u8"
          }
        ]
      }
    }
  ]
}